color/__init__.py
color/color.py
color_alpa-0.0.6.dist-info/LICENSE
color_alpa-0.0.6.dist-info/WHEEL
color_alpa-0.0.6.dist-info/METADATA
color_alpa-0.0.6.dist-info/RECORD
